pyraat/__init__.py
pyraat/_version.py
pyraat/exceptions.py
pyraat/parse_outputs.py
pyraat/praat_script.py
pyraat/run_scripts.py
pyraat-1.0.0.dist-info/licenses/LICENSE
pyraat-1.0.0.dist-info/METADATA
pyraat-1.0.0.dist-info/WHEEL
pyraat-1.0.0.dist-info/top_level.txt
pyraat-1.0.0.dist-info/RECORD
